macrosim/EqSearch.py
macrosim/SimEngine.py
macrosim/SimState.py
macrosim/__init__.py
macrosim-0.0.14.dist-info/LICENSE
macrosim-0.0.14.dist-info/METADATA
macrosim-0.0.14.dist-info/WHEEL
macrosim-0.0.14.dist-info/RECORD
